djangomediapil/__init__.py
djangomediapil/config.py
djangomediapil/fields.py
djangomediapil/mediaPIL.py
djangomediapil/mixins.py
djangomediapil/widgets.py
djangomediapil/static/djangomediapil/widget.css
djangomediapil/static/djangomediapil/widget.js
djangomediapil/templates/djangomediapil/image_widget.html
django_media_pil-1.0.0.dist-info/METADATA
django_media_pil-1.0.0.dist-info/WHEEL
django_media_pil-1.0.0.dist-info/top_level.txt
django_media_pil-1.0.0.dist-info/RECORD
