Metadata-Version: 2.1
Name: django-media-pil
Version: 1.0.0
Summary: Simple widget for image manipulations by pillow in the Django Admin
Home-page: https://github.com/giorgi94/django-media-pil
Author: Giorgi Kakulashvili
Author-email: UNKNOWN
License: MIT
Keywords: django,pillow,mediamanager
Platform: OS Independent
Requires-Dist: Django (>=2.1.0)
Requires-Dist: Pillow (>=5.3.0)
Requires-Dist: pycrop (>=1.0.1)
